odoo/addons/ssi_service_quotation_lead/README.rst
odoo/addons/ssi_service_quotation_lead/__init__.py
odoo/addons/ssi_service_quotation_lead/__manifest__.py
odoo/addons/ssi_service_quotation_lead/models/__init__.py
odoo/addons/ssi_service_quotation_lead/models/crm_lead.py
odoo/addons/ssi_service_quotation_lead/models/service_quotation.py
odoo/addons/ssi_service_quotation_lead/static/description/icon.png
odoo/addons/ssi_service_quotation_lead/views/crm_lead_views.xml
odoo/addons/ssi_service_quotation_lead/views/service_quotation_views.xml
odoo14_addon_ssi_service_quotation_lead-14.0.1.0.0.dist-info/METADATA
odoo14_addon_ssi_service_quotation_lead-14.0.1.0.0.dist-info/WHEEL
odoo14_addon_ssi_service_quotation_lead-14.0.1.0.0.dist-info/top_level.txt
odoo14_addon_ssi_service_quotation_lead-14.0.1.0.0.dist-info/RECORD
